cctrlw/__init__.py
cctrlw/algo.py
cctrlw/cli.py
cctrlw_config/cw_modes.json
xontrib/xonsh_cctrlw.py
cctrlw-0.5.dist-info/LICENSE
cctrlw-0.5.dist-info/METADATA
cctrlw-0.5.dist-info/WHEEL
cctrlw-0.5.dist-info/top_level.txt
cctrlw-0.5.dist-info/RECORD
