Metadata-Version: 2.1
Name: cctrlw
Version: 0.5
Summary: Configurable Ctrl-W algorithm, xontrib and CLI.
Home-page: https://github.com/ggdwbg/cctrlw
Author: Maxim Yurchenkov
Author-email: ggdwbg@gmail.com
License: MIT
Download-URL: https://pypi.python.org/cctrlw/
Platform: any
Classifier: Intended Audience :: End Users/Desktop
Classifier: License :: Freeware
Classifier: Programming Language :: Python
License-File: LICENSE
Requires-Dist: cctrlw
